Re/w03/ha/ha.v
module ha (
    input   wire        i_a,
    input   wire        i_b,
    output  wire        o_sum,
    output  wire        o_carry
);

/*
a b s c
0 0 0 0
0 1 1 0
1 0 1 0
1 1 0 1
*/
assign o_sum = i_a ^ i_b;
assign o_carry = i_a & i_b;

endmodule

Re/w03/ha/ha_tb.v
`timescale 1ns/1ns

module ha_tb();

reg [1:0]test_sig;

initial
begin
    $dumpfile("ha_tb.vcd");
    $dumpvars(1);
end

initial begin
    test_sig = 0;
    
    repeat(16)
    begin
        #10;
        test_sig = test_sig + 1;
    end
end

ha      u_test
(
    .i_a        (test_sig[0]),
    .i_b        (test_sig[1]),
    .o_sum      (o_sum),
    .o_carry    (o_carry)
);

endmodule

Re/w03/ha/ha_tb.vcd
$date
	Sat Apr 13 16:46:32 2024
$end
$version
	Icarus Verilog
$end
$timescale
	1ns
$end
$scope module ha_tb $end
$var wire 1 ! o_sum $end
$var wire 1 " o_carry $end
$var reg 2 # test_sig [1:0] $end
$upscope $end
$enddefinitions $end
$comment Show the parameter values. $end
$dumpall
$end
#0
$dumpvars
b0 #
0"
0!
$end
#10
1!
b1 #
#20
b10 #
#30
0!
1"
b11 #
#40
0"
b0 #
#50
1!
b1 #
#60
b10 #
#70
0!
1"
b11 #
#80
0"
b0 #
#90
1!
b1 #
#100
b10 #
#110
0!
1"
b11 #
#120
0"
b0 #
#130
1!
b1 #
#140
b10 #
#150
0!
1"
b11 #
#160
0"
b0 #
