w06/comparator/comparator_2bit.v
module comparator_2bit (
    input    wire            i_a,
    input    wire            i_b,
    output   wire            o_equal,
    output   wire            o_not_equal,
    output   wire            o_great_a,
    output   wire            o_great_b
);

assign  o_equal      = (i_a == i_b) ? 1'b1 : 1'b0;
assign  o_not_equal  = (i_a != i_b) ? 1'b1 : 1'b0;
assign  o_great_a    = (i_a > i_b)  ? 1'b1 : 1'b0;
assign  o_great_b    = (i_a < i_b)  ? 1'b1 : 1'b0;

endmodule

w06_comparator_decoer/comparator/tb_comparator_2bit.v
`timescale 1ns/1ns

module tb_comparator_2bit ();

reg [1:0] test_sig;

initial begin
    test_sig = 0;
    
    repeat(16)
    begin
        #10;
        test_sig = test_sig + 1;
    end
end

wire w_equal, w_not_equal, w_great_a, w_great_b;

comparator_2bit     u_test
(
    .i_a            (test_sig[0]),
    .i_b            (test_sig[1]),
    .o_equal        (w_equal),
    .o_not_equal    (w_not_equal),
    .o_great_a      (w_great_a),
    .o_great_b      (w_great_b)
);

initial begin
    $dumpfile("tb_comp.vcd");
    $dumpvars(1);
end

endmodule

w06/comparator/tb_comp.vcd
$date
	Mon Apr 15 22:55:50 2024
$end
$version
	Icarus Verilog
$end
$timescale
	1ns
$end
$scope module tb_comparator_2bit $end
$var wire 1 ! w_not_equal $end
$var wire 1 " w_great_b $end
$var wire 1 # w_great_a $end
$var wire 1 $ w_equal $end
$var reg 2 % test_sig [1:0] $end
$upscope $end
$enddefinitions $end
$comment Show the parameter values. $end
$dumpall
$end
#0
$dumpvars
b0 %
1$
0#
0"
0!
$end
#10
0$
1!
1#
b1 %
#20
1"
0#
b10 %
#30
1$
0!
0"
b11 %
#40
b0 %
#50
0$
1!
1#
b1 %
#60
1"
0#
b10 %
#70
1$
0!
0"
b11 %
#80
b0 %
#90
0$
1!
1#
b1 %
#100
1"
0#
b10 %
#110
1$
0!
0"
b11 %
#120
b0 %
#130
0$
1!
1#
b1 %
#140
1"
0#
b10 %
#150
1$
0!
0"
b11 %
#160
b0 %
