w03_ha/half_adder.v
module half_adder (
    input   wire    i_a,
    input   wire    i_b,
    output  wire    o_sum,
    output  wire    o_carry
);

assign o_sum = i_a ^ i_b;
assign o_carry = i_a & i_b;
    
endmodule

w04_fa/full_adder_2ha.v
module full_adder_2ha (
    input   wire        i_a,
    input   wire        i_b,
    input   wire        i_cin,
    output  wire        o_sum,
    output  wire        o_cout
);

wire  w_sum;
wire  w_carry_1, w_carry_2;

half_adder      u_ha_1
(
    .i_a        (i_a        ),
    .i_b        (i_b        ),
    .o_sum      (w_sum      ),
    .o_carry    (w_carry_1  )
);

half_adder      u_ha_2
(
    .i_a        (w_sum     ),
    .i_b        (i_cin      ),
    .o_sum      (o_sum      ),
    .o_carry    (w_carry_2  )
);

wire  w_cout = w_carry_1 | w_carry_2;
assign  o_cout = w_cout;

endmodule

w04_fa/tb.v
module tb();

reg [2:0] test_sig;

initial
begin
    test_sig = 0;
    repeat (20) begin
        #10 test_sig = test_sig + 1;
    end
end

initial
begin
    $dumpfile("tb.vcd");
    $dumpvars(1);
end

wire  w_sum;
wire  w_cout;

full_adder_2ha    u_test_full
(
    .i_a        (test_sig[2]  ),
    .i_b        (test_sig[1]  ),
    .i_cin      (test_sig[0]  ),
    .o_sum      (w_sum          ),
    .o_cout     (w_cout         )
);

endmodule

w04_fa/tb.vcd
$date
	Wed Mar 27 13:52:41 2024
$end
$version
	Icarus Verilog
$end
$timescale
	1s
$end
$scope module tb $end
$var wire 1 ! w_sum $end
$var wire 1 " w_cout $end
$var reg 3 # test_sig [2:0] $end
$upscope $end
$enddefinitions $end
$comment Show the parameter values. $end
$dumpall
$end
#0
$dumpvars
b0 #
0"
0!
$end
#10
1!
b1 #
#20
1!
b10 #
#30
0!
1"
b11 #
#40
1!
0"
b100 #
#50
0!
1"
b101 #
#60
0!
b110 #
#70
1!
b111 #
#80
0"
0!
b0 #
#90
1!
b1 #
#100
1!
b10 #
#110
0!
1"
b11 #
#120
1!
0"
b100 #
#130
0!
1"
b101 #
#140
0!
b110 #
#150
1!
b111 #
#160
0"
0!
b0 #
#170
1!
b1 #
#180
1!
b10 #
#190
0!
1"
b11 #
#200
1!
0"
b100 #
