Re/w04/fa/ha.v
module ha(
    input   wire    i_a,
    input   wire    i_b,
    output  wire    o_sum,
    output  wire    o_carry
);

assign o_sum = i_a ^ i_b;
assign o_carry = i_a & i_b;

endmodule

Re/w05/adder_4bit/fa.v
module fa (
    input   wire    i_a,
    input   wire    i_b,
    input   wire    i_cin,
    output  wire    o_sum,
    output  wire    o_cout
);

// module instatiaion
ha      ha_1
(
    .i_a            (i_a        ),
    .i_b            (i_b        ),
    .o_sum          (w_sum      ),
    .o_carry        (w_carry_1  )
);

wire w_sum;

ha      ha_2
(
    .i_a            (w_sum      ),
    .i_b            (i_cin      ),
    .o_sum          (o_sum      ),
    .o_carry        (w_carry_2  )
);

wire w_carry_1, w_carry_2;

assign o_cout = w_carry_1 | w_carry_2;
    
endmodule

Re/w04/fa/fa_tb.v
`timescale 1ns/1ns

module fa_tb();

reg [2:0] test_sig;

// 00 01 10 11 test_signal
initial begin
    test_sig = 0;

    repeat (16) begin
        #10 test_sig = test_sig + 1;
    end
end

fa      u_test_fa
(
    .i_a    (test_sig[0]    ),
    .i_b    (test_sig[1]    ),
    .i_cin  (test_sig[2]    ),
    .o_sum  (o_sum          ),
    .o_cout (o_cout         )
);

initial begin
    $dumpfile("fa_tb.vcd");
    $dumpvars(1);
end

endmodule

Re/w04/fa/fa_tb.vcd
$date
	Sat Apr 13 17:32:25 2024
$end
$version
	Icarus Verilog
$end
$timescale
	1ns
$end
$scope module fa_tb $end
$var wire 1 ! o_sum $end
$var wire 1 " o_cout $end
$var reg 3 # test_sig [2:0] $end
$upscope $end
$enddefinitions $end
$comment Show the parameter values. $end
$dumpall
$end
#0
$dumpvars
b0 #
0"
0!
$end
#10
1!
b1 #
#20
b10 #
#30
0!
1"
b11 #
#40
0"
1!
b100 #
#50
1"
0!
b101 #
#60
b110 #
#70
1!
b111 #
#80
0"
0!
b0 #
#90
1!
b1 #
#100
b10 #
#110
0!
1"
b11 #
#120
0"
1!
b100 #
#130
1"
0!
b101 #
#140
b110 #
#150
1!
b111 #
#160
0"
0!
b0 #
