w05/half_adder.v
module half_adder (
    input   wire        i_a,
    input   wire        i_b,
    output  wire        o_sum,
    output  wire        o_carry
);
    
assign o_sum = (~i_a & i_b) | (i_a & ~i_b);
assign o_carry = i_a & i_b;

endmodule

w04_fa/full_adder_2ha.v
module full_adder_2ha (
    input   wire        i_a,
    input   wire        i_b,
    input   wire        i_cin,
    output  wire        o_sum,
    output  wire        o_cout
);

wire  w_sum;
wire  w_carry_1, w_carry_2;

half_adder      u_ha_1
(
    .i_a        (i_a        ),
    .i_b        (i_b        ),
    .o_sum      (w_sum      ),
    .o_carry    (w_carry_1  )
);

half_adder      u_ha_2
(
    .i_a        (w_sum     ),
    .i_b        (i_cin      ),
    .o_sum      (o_sum      ),
    .o_carry    (w_carry_2  )
);

wire  w_cout = w_carry_1 | w_carry_2;
assign  o_cout = w_cout;

endmodule

w05/adder_4bit.v
module adder_4bit
(
    input   wire    [3:0]   i_a,
    input   wire    [3:0]   i_b,
    input   wire            i_cin,
    output  wire    [3:0]   o_sum,
    output  wire            o_cout
);

wire    w_cin_0, w_cin_1, w_cin_2;

full_adder_2ha  u_fa0
(
    .i_a        (i_a[0]     ),
    .i_b        (i_b[0]     ),
    .i_cin      (i_cin      ),
    .o_sum      (o_sum[0]   ),
    .o_cout     (w_cin_0    )
);

full_adder_2ha  u_fa1
(
    .i_a        (i_a[1]     ),
    .i_b        (i_b[1]     ),
    .i_cin      (w_cin_0    ),
    .o_sum      (o_sum[1]   ),
    .o_cout     (w_cin_1    )
);

full_adder_2ha  u_fa2
(
    .i_a        (i_a[2]     ),
    .i_b        (i_b[2]     ),
    .i_cin      (w_cin_1    ),
    .o_sum      (o_sum[2]   ),
    .o_cout     (w_cin_2    )
);

full_adder_2ha  u_fa3
(
    .i_a        (i_a[3]     ),
    .i_b        (i_b[3]     ),
    .i_cin      (w_cin_2    ),
    .o_sum      (o_sum[3]   ),
    .o_cout     (o_cout     )
);


endmodule

w05_adder4bit/tb.v
`timescale 1ns / 1ns

module tb();

reg  [3:0]  r_a, r_b;
reg         r_cin;

initial
begin
    $dumpfile("tb_adder_4bit.vcd");
    $dumpvars(1);
end

// 각 i_a, i_b, i_cin 에 랜덤한 숫자 넣기
initial
begin
    r_a = 0;
    r_b = 0;
    r_cin = 0;

    repeat(20)
    begin
        #10;
        r_a = $urandom;
        r_b = $urandom;
        r_cin = $urandom;
    end
end

// 출력이 정확한지 판단할 수 있는 신호 만들기
wire    [4:0]  w_answer;
assign w_answer = r_a + r_b + r_cin;

wire    [3:0]  w_ref_sum; 
wire           w_ref_cout;
assign w_ref_sum = w_answer[3:0];
assign w_ref_cout = w_answer[4];

// 신호 instanciation & port mapping
wire    [3:0]   w_sum;
wire            w_cout;

adder_4bit  u_adder_4
(
    .i_a        (r_a    ),
    .i_b        (r_b    ),
    .i_cin      (r_cin  ),
    .o_sum      (w_sum  ),
    .o_cout     (w_cout )
);


always @(r_a or r_b or r_cin)
begin
    if ((w_sum == w_ref_sum) && (w_cout == w_ref_cout))
    begin
        $display("%d ns : Correct Operation", $time);
    end
    else
    begin
        $display("%d ns : Error", $time);
        $display("i_a = %d, i_b = %d, i_cin = %b, o_sum = %d, o_cout = %b",
                  r_a, r_b, r_cin, w_sum, w_cout);
        $stop;
    end
end


endmodule

w05/tb_adder_4bit.vcd
$date
	Thu Mar 28 15:17:17 2024
$end
$version
	Icarus Verilog
$end
$timescale
	1ns
$end
$scope module tb $end
$var wire 4 ! w_sum [3:0] $end
$var wire 4 " w_ref_sum [3:0] $end
$var wire 1 # w_ref_cout $end
$var wire 1 $ w_cout $end
$var wire 5 % w_answer [4:0] $end
$var reg 4 & r_a [3:0] $end
$var reg 4 ' r_b [3:0] $end
$var reg 1 ( r_cin $end
$upscope $end
$enddefinitions $end
$comment Show the parameter values. $end
$dumpall
$end
#0
$dumpvars
0(
b0 '
b0 &
b0 %
0$
0#
b0 "
b0 !
$end
#10
b110 !
b110 "
1(
b1 '
b110 %
b100 &
#20
1$
b1 !
1#
b1 "
b1101 '
b10001 %
b11 &
#30
b1000 !
0$
0#
b1000 "
b10 '
b1000 %
b101 &
#40
b100 !
1$
b100 "
1#
b110 '
b10100 %
b1101 &
#50
b1010 !
b1010 "
b11010 %
b1100 '
#60
b1011 !
0$
0#
b1011 "
0(
b101 '
b1011 %
b110 &
#70
b1100 !
b1100 "
b111 '
b1100 %
b101 &
#80
1$
b1 !
b1 "
1#
b10 '
b10001 %
b1111 &
#90
0$
b1101 !
b1101 "
0#
b101 '
b1101 %
b1000 &
#100
b1011 !
1$
b1011 "
1#
1(
b1101 '
b11011 %
b1101 &
#110
0$
b1101 !
0#
b1101 "
0(
b1010 '
b1101 %
b11 &
#120
b1011 !
b1011 "
1(
b1011 %
b0 &
#130
b1010 !
b1010 "
b11 '
b1010 %
b110 &
#140
b1111 !
0$
b1111 "
b1011 '
b1111 %
b11 &
#150
1$
b1 !
1#
b1 "
b1110 '
b10001 %
b10 &
#160
b10 !
b10 "
0(
b11 '
b10010 %
b1111 &
#170
b110 !
b110 "
b1100 '
b10110 %
b1010 &
#180
b1011 !
0$
b1011 "
0#
b1011 %
b1 '
#190
b10 !
1$
1#
b10 "
1(
b1001 '
b10010 %
b1000 &
#200
b1100 !
0$
0#
b1100 "
0(
b110 '
b1100 %
b110 &
