w06_comparator_decoer/decoder/decoder_2x4_case.v
module decoder_2x4_case (
    input   wire    [1:0]   i_a,
    output  reg     [3:0]   o_y
);

always @(i_a)
begin
    case (i_a)
        2'b00 :
            o_y = 4'b1011;
        2'b01 :
            o_y = 4'b0110;
        2'b10 :
            o_y = 4'b0101;
        2'b11 :
            o_y = 4'b1101;
    endcase 
end

endmodule

w06_comparator_decoer/decoder/tb_case.v
`timescale 1ns/1ns

module tb_case ();

reg [1:0] test_sig;

initial begin
    test_sig = 0;

    repeat(16) begin
        #10;
        test_sig = test_sig + 1;
    end
end

wire [3:0] w_y;

decoder_2x4_case  u_case_decoder
(
    .i_a(test_sig),
    .o_y(w_y)  
);

initial begin
    $dumpfile("tb_case.vcd");
    $dumpvars(1);
end
endmodule

w06/decoder/tb_case.vcd
$date
	Mon Apr 15 21:17:14 2024
$end
$version
	Icarus Verilog
$end
$timescale
	1ns
$end
$scope module tb_case $end
$var wire 4 ! w_y [3:0] $end
$var reg 2 " test_sig [1:0] $end
$upscope $end
$enddefinitions $end
$comment Show the parameter values. $end
$dumpall
$end
#0
$dumpvars
b0 "
b1011 !
$end
#10
b110 !
b1 "
#20
b101 !
b10 "
#30
b1101 !
b11 "
#40
b1011 !
b0 "
#50
b110 !
b1 "
#60
b101 !
b10 "
#70
b1101 !
b11 "
#80
b1011 !
b0 "
#90
b110 !
b1 "
#100
b101 !
b10 "
#110
b1101 !
b11 "
#120
b1011 !
b0 "
#130
b110 !
b1 "
#140
b101 !
b10 "
#150
b1101 !
b11 "
#160
b1011 !
b0 "
