Re/w05/add_sub_4bit/fa.v
module fa (
    input   wire        i_a,
    input   wire        i_b,
    input   wire        i_cin,
    output  wire        o_sum,
    output  wire        o_cout
);

/*
    0 0 0   0 0
    0 0 1   1 0
    0 1 0   1 0
    0 1 1   0 1
    1 0 0   1 0
    1 0 1   0 1
    1 1 0   0 1
    1 1 1   1 1
*/
wire w_m;
assign w_m = i_a ^ i_b; // 
assign o_sum = w_m ^ i_cin;
assign o_cout = (i_cin & w_m) | (i_a & i_b);

endmodule

Re/w05/add_sub_4bit/adder_4bit.v
module adder_4bit (
    input   wire  [3:0]     i_a,
    input   wire  [3:0]     i_b,
    input   wire            i_cin,
    output  wire  [3:0]     o_sum,
    output  wire            o_cout
);


fa      u_fa_0
(
    .i_a            (i_a[0]),
    .i_b            (i_b[0]),
    .i_cin          (i_cin),
    .o_sum          (o_sum[0]),
    .o_cout         (w_carry_0)
);

wire w_carry_0;

fa      u_fa_1
(
    .i_a            (i_a[1]),
    .i_b            (i_b[1]),
    .i_cin          (w_carry_0),
    .o_sum          (o_sum[1]),
    .o_cout         (w_carry_1)
);

wire w_carry_1;

fa      u_fa_2
(
    .i_a            (i_a[2]),
    .i_b            (i_b[2]),
    .i_cin          (w_carry_1),
    .o_sum          (o_sum[2]),
    .o_cout         (w_carry_2)
);

wire w_carry_2;

fa      u_fa_3
(
    .i_a            (i_a[3]),
    .i_b            (i_b[3]),
    .i_cin          (w_carry_2),
    .o_sum          (o_sum[3]),
    .o_cout         (o_cout)
);

endmodule

Re/w05/add_sub_4bit/add_sub.v
module add_sub (
    input   wire  [3:0]     i_a,
    input   wire  [3:0]     i_b,
    input                   i_s,
    output  wire  [3:0]     o_sum,
    output  wire            o_cout
);

wire [3:0] w_b;
assign w_b[0] = i_b[0] ^ i_s;
assign w_b[1] = i_b[1] ^ i_s;
assign w_b[2] = i_b[2] ^ i_s;
assign w_b[3] = i_b[3] ^ i_s;

adder_4bit          u_adder
(
    .i_a        (i_a),
    .i_b        (w_b),
    .i_cin      (i_s),
    .o_sum      (o_sum),
    .o_cout     (o_cout)
);

endmodule

Re/w05/add_sub_4bit/tb_add_sub.v
`timescale 1ns/1ns

module tb_add_sub ();

reg [3:0] r_a;
reg [3:0] r_b;
reg r_s;

initial begin
    r_a = 0;
    r_b = 0;
    r_s = 0;

    repeat(32)
    begin
        #10;
        r_a = $urandom;
        r_b = $urandom;
        r_s = $urandom;        
    end
end

add_sub         u_test
(
    .i_a        (r_a),
    .i_b        (r_b),
    .i_s        (r_s),
    .o_sum      (w_sum),
    .o_cout     (w_cout)
);

wire [3:0] w_sum;
wire w_cout;

initial begin
    $dumpfile("tb_add_sub.vcd");
    $dumpvars(1);
end

endmodule

Re/w05/add_sub_4bit/tb_add_sub.vcd
$date
	Sun Apr 14 17:28:58 2024
$end
$version
	Icarus Verilog
$end
$timescale
	1ns
$end
$scope module tb_add_sub $end
$var wire 4 ! w_sum [3:0] $end
$var wire 1 " w_cout $end
$var reg 4 # r_a [3:0] $end
$var reg 4 $ r_b [3:0] $end
$var reg 1 % r_s $end
$upscope $end
$enddefinitions $end
$comment Show the parameter values. $end
$dumpall
$end
#0
$dumpvars
0%
b0 $
b0 #
0"
b0 !
$end
#10
1"
b11 !
1%
b1 $
b100 #
#20
0"
b110 !
b1101 $
b11 #
#30
1"
b11 !
b10 $
b101 #
#40
b111 !
b110 $
b1101 #
#50
b1 !
1"
b1100 $
#60
0"
b1011 !
0%
b101 $
b110 #
#70
b1100 !
b111 $
b101 #
#80
1"
b1 !
b10 $
b1111 #
#90
0"
b1101 !
b101 $
b1000 #
#100
1"
b0 !
1%
b1101 $
b1101 #
#110
0"
b1101 !
0%
b1010 $
b11 #
#120
b110 !
1%
b0 #
#130
1"
b11 !
b11 $
b110 #
#140
0"
b1000 !
b1011 $
b11 #
#150
b100 !
b1110 $
b10 #
#160
1"
b10 !
0%
b11 $
b1111 #
#170
b110 !
b1100 $
b1010 #
#180
b1011 !
0"
b1 $
#190
0"
b1111 !
1%
b1001 $
b1000 #
#200
b1100 !
0%
b110 $
b110 #
#210
1"
b10 !
1%
b1010 $
b1100 #
#220
0"
b1100 !
b101 $
b1 #
#230
1"
b101 !
0%
b1010 $
b1011 #
#240
1"
b100 !
1%
b1 $
b101 #
#250
0"
b110 !
b1100 $
b10 #
#260
1"
b111 !
b1000 $
b1111 #
#270
1"
b11 !
b1100 $
#280
b10 !
0%
b1001 $
b1001 #
#290
b1000 !
0"
b1 $
b111 #
#300
0"
b1110 !
b10 $
b1100 #
#310
1"
b100 !
b1101 $
b111 #
#320
1"
b1 !
1%
b1110 #
