w09_acc_add_counter/acc/acc_8bit.v
module acc_8bit (
    input   wire            i_clk,
    input   wire            i_rst_n,
    input   wire            i_enable,
    input   wire            i_init,
    input   wire    [7:0]   i_in,
    output  reg     [15:0]  o_acc
);

always @(posedge i_clk or negedge i_rst_n) begin
    if (~i_rst_n)
        o_acc <= 0;
    else begin
        if (i_init)
            o_acc <= 0;
        else if (i_enable)
            o_acc <= o_acc + i_in;
    end
end

endmodule

w09_acc_add_counter/acc/testbench_acc_8bit.v
`timescale 1ns/1ns

module  testbench_acc_8bit();

initial begin
    $dumpfile("sim_acc.vcd");
    $dumpvars(1);
end

// clock test signal
reg    r_clk;

initial begin
    r_clk = 1'b0;
    repeat(40)
        #10 r_clk = ~r_clk;
end

// Reset(negedge) test signal
reg    r_rst_n;

initial begin
    r_rst_n = 1'b0;
    #40 r_rst_n = 1'b1;
end


// enable, init test signal
reg    r_enable;
reg    r_init;

initial begin
    r_enable = 0;
    r_init   = 0;
    @(posedge r_rst_n); // rst가 1이 (5번) 뜨는 순간 
    repeat(5) @(posedge r_clk); // 1이 5번뜨면 clk가 1이 뜨는 순간
    r_init = 1; // init = 1
    @(posedge r_clk); // clk가 1이 뜨는 순간(1 사이클)
    r_init = 0; // init = 0
    @(posedge r_clk); // clk가 1이 뜨는 순간(1 사이클)
    r_enable = 1; // enable = 1
    repeat(10) @(posedge r_clk); // 10 사이클 돌면
    r_enable = 0; // enable = 0
end

// in test signal
reg    [7:0]    r_in;

always  @(posedge r_clk)
begin
    if  (~r_rst_n)
      r_in = 8'd0;
    else
    begin
      if  (r_enable)
        r_in = r_in + 8'd1; 
    end
end

wire [15:0] w_acc;
acc_8bit        u_test_acc
(
    .i_clk      (r_clk      ),
    .i_rst_n    (r_rst_n    ),
    .i_enable   (r_enable   ),
    .i_init     (r_init     ),
    .i_in       (r_in       ),
    .o_acc      (w_acc      )
);

endmodule

w09/acc/sim_acc.vcd
$date
	Tue May  7 14:56:33 2024
$end
$version
	Icarus Verilog
$end
$timescale
	1ns
$end
$scope module testbench_acc_8bit $end
$var wire 16 ! w_acc [15:0] $end
$var reg 1 " r_clk $end
$var reg 1 # r_enable $end
$var reg 8 $ r_in [7:0] $end
$var reg 1 % r_init $end
$var reg 1 & r_rst_n $end
$upscope $end
$enddefinitions $end
$comment Show the parameter values. $end
$dumpall
$end
#0
$dumpvars
0&
0%
bx $
0#
0"
b0 !
$end
#10
b0 $
1"
#20
0"
#30
1"
#40
0"
1&
#50
1"
#60
0"
#70
1"
#80
0"
#90
1"
#100
0"
#110
1"
#120
0"
#130
1%
1"
#140
0"
#150
0%
1"
#160
0"
#170
b1 !
b1 $
1#
1"
#180
0"
#190
b11 !
b10 $
1"
#200
0"
#210
b110 !
b11 $
1"
#220
0"
#230
b1010 !
b100 $
1"
#240
0"
#250
b1111 !
b101 $
1"
#260
0"
#270
b10101 !
b110 $
1"
#280
0"
#290
b11100 !
b111 $
1"
#300
0"
#310
b100100 !
b1000 $
1"
#320
0"
#330
b101101 !
b1001 $
1"
#340
0"
#350
b110111 !
b1010 $
1"
#360
0"
#370
0#
1"
