w07/alu/alu_8bit_me.v
module alu_8bit_me (
    input   wire    [7:0]       i_a,
    input   wire    [7:0]       i_b,
    input   wire    [2:0]       i_op,
    output  reg     [7:0]       o_result,
    output  wire    [7:0]       o_flag
);
always @(*) begin
    case (i_op)
        0 : o_result = i_a + i_b;
        1 : o_result = i_a - i_b;
        2 : o_result = i_b - i_a;
        3 : o_result = i_a & i_b;
        4 : o_result = i_a | i_b;
        5 : o_result = i_a ^ i_b;
        6 : o_result = ~i_a;
        7 : o_result = 0;
    endcase
end

reg r_overflow;
always @(*) begin
    if (i_op == 0) begin // addition
        if (~i_a[7] & ~i_b[7] & o_result[7])
            r_overflow = 1;
        else if(i_a[7] & i_b[7] & ~o_result[7])
            r_overflow = 1;
        else
            r_overflow = 0;
    end
    else if (i_op == 1) begin // subtraction 1 : (a - b)
        if (~i_a[7] & i_b[7] & o_result[7])
            r_overflow = 1;
        else if(i_a[7] & ~i_b[7] & ~o_result[7])
            r_overflow = 1;
        else
            r_overflow = 0;
    end
    else if (i_op == 2) begin // subtraction 2 : (b - a)
        if (~i_b[7] & i_a[7] & o_result[7])
            r_overflow = 1;
        else if(i_b[7] & ~i_a[7] & ~o_result[7])
            r_overflow = 1;
        else
            r_overflow = 0;
    end
    else
        r_overflow = 0;
end


// 비교기
wire    w_zero;
wire    w_equal;
wire    w_not_equal;
wire    w_greater_a;
wire    w_greater_b; 

assign  w_zero = (i_op != 7) ? (o_result == 0) : 0; 
assign  w_equal = (i_op == 7) ? (i_a == i_b) : 0;
assign  w_not_equal = (i_op == 7) ? (i_a != i_b) : 0;
assign  w_greater_a = (i_op == 7) ? (i_a > i_b) : 0;
assign  w_greater_b = (i_op == 7) ? (i_a < i_b) : 0; 

assign  o_flag[0] = r_overflow;
assign  o_flag[1] = w_zero;
assign  o_flag[3:2] = 0;
assign  o_flag[4] = w_equal;
assign  o_flag[5] = w_not_equal;
assign  o_flag[6] = w_greater_a;
assign  o_flag[7] = w_greater_b; 
// assign  o_flag = {w_greater_b, w_greater_a, w_not_equal, w_equal, 2'b0, w_zero, r_overflow};

endmodule

w07_alu8bit/tb_alu_8bit.v
`timescale 1ns/1ns

module tb_alu_8bit();

reg	[2:0]	r_op;
reg	[7:0]	r_a, r_b;

initial
begin
	r_op = 0;   r_a = 0;    r_b = 0;

    // Addition without overflow
    #10 r_op = 0;   r_a = 8'd25;    r_b = 8'd77;

    // Addition with overflow
    #10 r_op = 0;   r_a = 8'd50;    r_b = 8'd110;

    // Addition with overflow
    #10 r_op = 0;   r_a = -8'd50;    r_b = -8'd99;

    // Addition with zero
    #10 r_op = 0;   r_a = 8'd111;    r_b = -8'd111;

    // Subtraction1 without overflow
    #10 r_op = 1;   r_a = 8'd100;    r_b = 8'd45;

    // Subtraction1 with overflow
    #10 r_op = 1;   r_a = 8'd57;    r_b = -8'd86;

    // Subtraction1 with overflow
    #10 r_op = 1;   r_a = -8'd62;    r_b = 8'd93;

    // Subtraction1 with zero
    #10 r_op = 1;   r_a = 8'd123;    r_b = 8'd123;

    // Subtraction2 without overflow
    #10 r_op = 2;   r_a = 8'd100;    r_b = 8'd45;

    // Subtraction2 with overflow
    #10 r_op = 2;   r_a = 8'd57;    r_b = -8'd86;

    // Subtraction2 with overflow
    #10 r_op = 2;   r_a = -8'd62;    r_b = 8'd93;

    // Subtraction2 with zero
    #10 r_op = 2;   r_a = 8'd78;    r_b = 8'd78;

    // AND
    #10 r_op = 3;   r_a = 8'b11111111;  r_b = 8'b01010101;

    // AND with zero
    #10 r_op = 3;   r_a = 8'b01010101;  r_b = 8'b10101010;

    // OR
    #10 r_op = 4;   r_a = 8'b11110000;  r_b = 8'b11001100;

    // OR with zero
    #10 r_op = 4;   r_a = 8'b00000000;  r_b = 8'b00000000;

    // XOR
    #10 r_op = 5;   r_a = 8'b00001111;  r_b = 8'b00110011;

    // XOR with zero
    #10 r_op = 5;   r_a = 8'b11110000;  r_b = 8'b11110000;

    // NOT
    #10 r_op = 6;   r_a = 8'b11001100;  r_b = 8'b00000000;

    // NOT
    #10 r_op = 6;   r_a = 8'b11111111;  r_b = 8'b00000000;

    // Compare Equal
    #10 r_op = 7;   r_a = 8'd100;    r_b = 8'd100;

    // Compare Not Equal
    #10 r_op = 7;   r_a = 8'd100;    r_b = 8'd101;

    // Compare Greater A
    #10 r_op = 7;   r_a = 8'd100;    r_b = 8'd10;

    // Compare Greater B
    #10 r_op = 7;   r_a = 8'd100;    r_b = 8'd110;
end

wire    [7:0]   w_result, w_flag;

alu_8bit_me    u_dut
(
    .i_op           (r_op           ),
    .i_a            (r_a            ),
    .i_b            (r_b            ),
    .o_result       (w_result       ),
    .o_flag         (w_flag         )
);

initial begin
    $dumpfile("tb_alu.vcd");
    $dumpvars(1);
end

endmodule

w07_alu8bit/tb_alu.vcd
$date
	Tue Apr 16 16:31:13 2024
$end
$version
	Icarus Verilog
$end
$timescale
	1ns
$end
$scope module tb_alu_8bit $end
$var wire 8 ! w_result [7:0] $end
$var wire 8 " w_flag [7:0] $end
$var reg 8 # r_a [7:0] $end
$var reg 8 $ r_b [7:0] $end
$var reg 3 % r_op [2:0] $end
$upscope $end
$enddefinitions $end
$comment Show the parameter values. $end
$dumpall
$end
#0
$dumpvars
b0 %
b0 $
b0 #
b0 "
b0 !
$end
#10
b1100110 !
b1001101 $
b11001 #
#20
b1 "
b10100000 !
b1101110 $
b110010 #
#30
b1101011 !
b10011101 $
b11001110 #
#40
b0 "
b0 !
b10010001 $
b1101111 #
#50
b110111 !
b101101 $
b1100100 #
b1 %
#60
b1 "
b10001111 !
b10101010 $
b111001 #
#70
b1100101 !
b1011101 $
b11000010 #
#80
b0 "
b0 !
b1111011 $
b1111011 #
#90
b11001001 !
b101101 $
b1100100 #
b10 %
#100
b1 "
b1110001 !
b10101010 $
b111001 #
#110
b10011011 !
b1011101 $
b11000010 #
#120
b0 "
b0 !
b1001110 $
b1001110 #
#130
b1010101 !
b1010101 $
b11111111 #
b11 %
#140
b0 !
b10101010 $
b1010101 #
#150
b11111100 !
b11001100 $
b11110000 #
b100 %
#160
b0 !
b0 $
b0 #
#170
b111100 !
b110011 $
b1111 #
b101 %
#180
b0 !
b11110000 $
b11110000 #
#190
b110011 !
b0 $
b11001100 #
b110 %
#200
b0 !
b11111111 #
#210
b10010 "
b1100100 $
b1100100 #
b111 %
#220
b10100010 "
b1100101 $
#230
b1100010 "
b1010 $
#240
b10100010 "
b1101110 $
