Re/w02/first/first_module.v
module first_module(
    input   wire    [1:0]    first_in,
    output  wire    [2:0]    first_out1,
    output  wire    [2:0]    first_out2,
    output  wire    [2:0]    first_out3
);

assign first_out1= first_in[0] & first_in[1];
assign first_out2= first_in[0] | first_in[1];
assign first_out3= first_in[0] ^ first_in[1];

endmodule

Re/w02/first/first_tb.v
`timescale 1ns/1ns

module first_tb();

reg [1:0] test_sig;


initial begin
    test_sig = 0;

    repeat(8) begin
        #10;
        test_sig = test_sig + 1;
    end
end

initial begin
    $dumpfile("first_tb.vcd");
    $dumpvars(1);
end

first_module      u_test_sig
(
    .first_in         (test_sig),
    .first_out1       (first_out1),
    .first_out2       (first_out2),
    .first_out3       (first_out3)
);

endmodule

Re/w02/first/first_tb.vcd
$date
	Wed Apr 10 23:00:05 2024
$end
$version
	Icarus Verilog
$end
$timescale
	1ns
$end
$scope module first_tb $end
$var wire 1 ! first_out3 $end
$var wire 1 " first_out2 $end
$var wire 1 # first_out1 $end
$var reg 2 $ test_sig [1:0] $end
$upscope $end
$enddefinitions $end
$comment Show the parameter values. $end
$dumpall
$end
#0
$dumpvars
b0 $
0#
0"
0!
$end
#10
1"
1!
b1 $
#20
b10 $
#30
1#
0!
b11 $
#40
0#
0"
b0 $
#50
1"
1!
b1 $
#60
b10 $
#70
1#
0!
b11 $
#80
0#
0"
b0 $
