Re/w03/ha/ha.v
module ha (
    input   wire        i_a,
    input   wire        i_b,
    output  wire        o_sum,
    output  wire        o_carry
);

/*
a b s c
0 0 0 0
0 1 1 0
1 0 1 0
1 1 0 1
*/
assign o_sum = i_a ^ i_b;
assign o_carry = i_a & i_b;

endmodule

Re/w05/adder_4bit/fa.v
module fa (
    input   wire    i_a,
    input   wire    i_b,
    input   wire    i_cin,
    output  wire    o_sum,
    output  wire    o_cout
);

// module instatiaion
ha      ha_1
(
    .i_a            (i_a        ),
    .i_b            (i_b        ),
    .o_sum          (w_sum      ),
    .o_carry        (w_carry_1  )
);

wire w_sum;

ha      ha_2
(
    .i_a            (w_sum      ),
    .i_b            (i_cin      ),
    .o_sum          (o_sum      ),
    .o_carry        (w_carry_2  )
);

wire w_carry_1, w_carry_2;

assign o_cout = w_carry_1 | w_carry_2;
    
endmodule

Re/w05/adder_4bit/adder_4bit.v
module adder_4bit(
    input   wire    [3:0]   i_a,
    input   wire    [3:0]   i_b,
    input   wire            i_cin,
    output  wire    [3:0]   o_sum,
    output  wire            o_cout
);

wire w_cout_0;

fa      u_fa_0
(
    .i_a            (i_a[0]         ),
    .i_b            (i_b[0]         ),
    .i_cin          (i_cin          ),
    .o_sum          (o_sum[0]       ),
    .o_cout         (w_cout_0       )
);

fa      u_fa_1
(
    .i_a            (i_a[1]         ),
    .i_b            (i_b[1]         ),
    .i_cin          (w_cout_0       ),
    .o_sum          (o_sum[1]       ),
    .o_cout         (w_cout_1       )
);

wire w_cout_1;

fa      u_fa_2
(
    .i_a            (i_a[2]         ),
    .i_b            (i_b[2]         ),
    .i_cin          (w_cout_1       ),
    .o_sum          (o_sum[2]       ),
    .o_cout         (w_cout_2       )
);

wire w_cout_2;

fa      u_fa_3
(
    .i_a            (i_a[3]         ),
    .i_b            (i_b[3]         ),
    .i_cin          (w_cout_2       ),
    .o_sum          (o_sum[3]       ),
    .o_cout         (o_cout         )
);


endmodule

Re/w05/adder_4bit/adder_tb.v
`timescale 1ns/1ns

module adder_tb();

reg [3:0] r_a, r_b;
reg       r_cin;

// 초기화 및 랜덤숫자 생성
initial begin
    r_a = 0;
    r_b = 0;
    r_cin = 0;

    repeat (32) begin
        #10;
        r_a = $urandom;
        r_b = $urandom;
        r_cin = $urandom;
    end
end

// 내가 만든 모듈이 실제 값과 맞는지 판단하기 위한 wire 생성
wire [4:0] w_answer;
assign w_answer = r_a + r_b + r_cin;

wire [3:0] w_ref_sum;
wire       w_ref_cout;
assign w_ref_sum = w_answer[3:0];
assign w_ref_cout = w_answer[4];

wire [3:0]  w_sum;
wire        w_cout;

adder_4bit      u_test_fa
(
    .i_a        (r_a        ),
    .i_b        (r_b        ),
    .i_cin      (r_cin      ),
    .o_sum      (w_sum      ),
    .o_cout     (w_cout     )
);

always @(r_a or r_b or r_cin)
begin
    if ((w_sum == w_ref_sum) && (w_cout == w_ref_cout))
    begin
        $display("%d ns : Correct Operation", $time);
        if ($time > 10000)
        $finish;
    end
    else
    begin
        $display("%d ns : Error", $time);
        $display("i_a = %d, i_b = %d, i_cin = %b, o_sum = %d, o_cout = %b",
                    r_a, r_b, r_cin, w_sum, w_cout);
        $stop;
    end
end

initial begin
    $dumpfile("adder_tb.vcd");
    $dumpvars(1);
end

endmodule

Re/w05/adder_4bit/adder_tb.vcd
$date
	Sat Apr 13 19:37:28 2024
$end
$version
	Icarus Verilog
$end
$timescale
	1ns
$end
$scope module adder_tb $end
$var wire 4 ! w_sum [3:0] $end
$var wire 4 " w_ref_sum [3:0] $end
$var wire 1 # w_ref_cout $end
$var wire 1 $ w_cout $end
$var wire 5 % w_answer [4:0] $end
$var reg 4 & r_a [3:0] $end
$var reg 4 ' r_b [3:0] $end
$var reg 1 ( r_cin $end
$upscope $end
$enddefinitions $end
$comment Show the parameter values. $end
$dumpall
$end
#0
$dumpvars
0(
b0 '
b0 &
b0 %
0$
0#
b0 "
b0 !
$end
#10
b110 !
b110 "
1(
b1 '
b110 %
b100 &
#20
1$
b1 !
1#
b1 "
b1101 '
b10001 %
b11 &
#30
0$
b1000 !
0#
b1000 "
b10 '
b1000 %
b101 &
#40
1$
b100 !
b100 "
1#
b110 '
b10100 %
b1101 &
#50
b1010 !
b1010 "
b11010 %
b1100 '
#60
0$
b1011 !
0#
b1011 "
0(
b101 '
b1011 %
b110 &
#70
b1100 !
b1100 "
b111 '
b1100 %
b101 &
#80
1$
b1 !
b1 "
1#
b10 '
b10001 %
b1111 &
#90
0$
b1101 !
b1101 "
0#
b101 '
b1101 %
b1000 &
#100
1$
b1011 !
b1011 "
1#
1(
b1101 '
b11011 %
b1101 &
#110
0$
b1101 !
0#
b1101 "
0(
b1010 '
b1101 %
b11 &
#120
b1011 !
b1011 "
1(
b1011 %
b0 &
#130
b1010 !
b1010 "
b11 '
b1010 %
b110 &
#140
0$
b1111 !
b1111 "
b1011 '
b1111 %
b11 &
#150
1$
b1 !
1#
b1 "
b1110 '
b10001 %
b10 &
#160
b10 !
b10 "
0(
b11 '
b10010 %
b1111 &
#170
b110 !
b110 "
b1100 '
b10110 %
b1010 &
#180
b1011 !
0$
b1011 "
0#
b1011 %
b1 '
#190
1$
b10 !
1#
b10 "
1(
b1001 '
b10010 %
b1000 &
#200
0$
b1100 !
0#
b1100 "
0(
b110 '
b1100 %
b110 &
#210
1$
b111 !
b111 "
1#
1(
b1010 '
b10111 %
b1100 &
#220
0$
0#
b101 '
b111 %
b1 &
#230
1$
b101 !
b101 "
1#
0(
b1010 '
b10101 %
b1011 &
#240
0$
b111 !
b111 "
0#
1(
b1 '
b111 %
b101 &
#250
0$
b1111 !
b1111 "
b1100 '
b1111 %
b10 &
#260
b1000 !
1$
b1000 "
1#
b1000 '
b11000 %
b1111 &
#270
b1100 !
b1100 "
b11100 %
b1100 '
#280
b10 !
b10 "
0(
b1001 '
b10010 %
b1001 &
#290
b1000 !
0$
0#
b1000 "
b1 '
b1000 %
b111 &
#300
0$
b1110 !
b1110 "
b10 '
b1110 %
b1100 &
#310
1$
b100 !
1#
b100 "
b1101 '
b10100 %
b111 &
#320
b1100 !
b1100 "
1(
b11100 %
b1110 &
